audiolm_pytorch/__init__.py
audiolm_pytorch/attend.py
audiolm_pytorch/audiolm_pytorch.py
audiolm_pytorch/data.py
audiolm_pytorch/encodec.py
audiolm_pytorch/hubert_kmeans.py
audiolm_pytorch/optimizer.py
audiolm_pytorch/soundstream.py
audiolm_pytorch/t5.py
audiolm_pytorch/trainer.py
audiolm_pytorch/utils.py
audiolm_pytorch/version.py
audiolm_pytorch/vq_wav2vec.py
audiolm_pytorch-2.3.1.dist-info/LICENSE
audiolm_pytorch-2.3.1.dist-info/METADATA
audiolm_pytorch-2.3.1.dist-info/WHEEL
audiolm_pytorch-2.3.1.dist-info/top_level.txt
audiolm_pytorch-2.3.1.dist-info/RECORD
